{
  "kind": "spec_vs_diff_report",
  "version": "1.0",
  "generatedAt": "2026-02-21T13:18:33.042Z",
  "summary": "The diff only updates project_state.json to track REQ-1 as a pending feature request. No actual deployment artifacts, configuration changes, or implementation evidence is present. The requirement to deploy to production on the Internet Computer network is completely missing from the implementation.",
  "missing_requirements": [
    {
      "id": "REQ-1",
      "requirement": "Deploy the current application version to the production environment on the Internet Computer network",
      "reason": "No deployment implementation detected. The diff only adds a tracking entry in project_state.json marking REQ-1 as 'pending'. Missing: deployment scripts, dfx.json production configuration, canister deployment commands, production network configuration, or any evidence of actual deployment to Internet Computer",
      "evidence": [
        "project_state.json"
      ]
    }
  ],
  "hallucinated_features": [],
  "confidence": 0.95,
  "changed_files": [
    "project_state.json"
  ]
}